atm/__init__.py
atm/classifier.py
atm/cli.py
atm/compat.py
atm/config.py
atm/constants.py
atm/core.py
atm/data.py
atm/database.py
atm/encoder.py
atm/method.py
atm/metrics.py
atm/utilities.py
atm/worker.py
atm/api/__init__.py
atm/api/utils.py
atm/config/aws.yaml
atm/config/config.yaml
atm/config/log-script.yaml
atm/config/log.yaml
atm/config/run.yaml
atm/config/sql.yaml
atm/methods/adaboost.json
atm/methods/bernoulli_naive_bayes.json
atm/methods/decision_tree.json
atm/methods/extra_trees.json
atm/methods/gaussian_naive_bayes.json
atm/methods/gaussian_process.json
atm/methods/k_nearest_neighbors.json
atm/methods/logistic_regression.json
atm/methods/multi_layer_perceptron.json
atm/methods/multinomial_naive_bayes.json
atm/methods/passive_aggressive.json
atm/methods/random_forest.json
atm/methods/stochastic_gradient_descent.json
atm/methods/support_vector_machine.json
atm-0.2.2.dist-info/AUTHORS.rst
atm-0.2.2.dist-info/LICENSE
atm-0.2.2.dist-info/METADATA
atm-0.2.2.dist-info/WHEEL
atm-0.2.2.dist-info/entry_points.txt
atm-0.2.2.dist-info/top_level.txt
atm-0.2.2.dist-info/RECORD
