Metadata-Version: 2.1
Name: atm
Version: 0.2.2
Summary: Auto Tune Models
Home-page: https://github.com/HDI-project/ATM
Author: MIT Data To AI Lab
Author-email: dailabmit@gmail.com
License: MIT license
Keywords: machine learning hyperparameters tuning classification
Platform: UNKNOWN
Classifier: Development Status :: 3 - Alpha
Classifier: Intended Audience :: Developers
Classifier: License :: OSI Approved :: MIT License
Classifier: Natural Language :: English
Classifier: Programming Language :: Python :: 2
Classifier: Programming Language :: Python :: 2.7
Classifier: Programming Language :: Python :: 3
Classifier: Programming Language :: Python :: 3.5
Classifier: Programming Language :: Python :: 3.6
Classifier: Topic :: Scientific/Engineering :: Artificial Intelligence
Requires-Dist: baytune (<0.3,>=0.2.5)
Requires-Dist: boto3 (<2,>=1.9.146)
Requires-Dist: future (<0.18,>=0.16.0)
Requires-Dist: pymysql (<0.10,>=0.9.3)
Requires-Dist: numpy (<1.17,>=1.13.1)
Requires-Dist: pandas (<0.25,>=0.22.0)
Requires-Dist: psutil (<6,>=5.6.1)
Requires-Dist: python-daemon (<3,>=2.2.3)
Requires-Dist: requests (<3,>=2.18.4)
Requires-Dist: scikit-learn (<0.22,>=0.18.2)
Requires-Dist: scipy (<1.4,>=0.19.1)
Requires-Dist: sqlalchemy (<1.4,>=1.1.14)
Requires-Dist: flask (<2,>=1.0.2)
Requires-Dist: flask-restless (<0.18,>=0.17.0)
Requires-Dist: flask-sqlalchemy (<2.5,>=2.3.2)
Requires-Dist: flask-restless-swagger-2 (==0.0.3)
Requires-Dist: simplejson (<4,>=3.16.0)
Requires-Dist: tqdm (<5,>=4.31.1)
Requires-Dist: docutils (<0.15,>=0.10)
Provides-Extra: dev
Requires-Dist: bumpversion (>=0.5.3) ; extra == 'dev'
Requires-Dist: pip (>=9.0.1) ; extra == 'dev'
Requires-Dist: watchdog (>=0.8.3) ; extra == 'dev'
Requires-Dist: m2r (>=0.2.0) ; extra == 'dev'
Requires-Dist: Sphinx (>=1.7.1) ; extra == 'dev'
Requires-Dist: sphinx-rtd-theme (>=0.2.4) ; extra == 'dev'
Requires-Dist: autodocsumm (>=0.1.10) ; extra == 'dev'
Requires-Dist: flake8 (>=3.7.7) ; extra == 'dev'
Requires-Dist: isort (>=4.3.4) ; extra == 'dev'
Requires-Dist: autoflake (>=1.1) ; extra == 'dev'
Requires-Dist: autopep8 (>=1.4.3) ; extra == 'dev'
Requires-Dist: twine (>=1.10.0) ; extra == 'dev'
Requires-Dist: wheel (>=0.30.0) ; extra == 'dev'
Requires-Dist: coverage (>=4.5.1) ; extra == 'dev'
Requires-Dist: tox (>=2.9.1) ; extra == 'dev'
Requires-Dist: mock (>=2.0.0) ; extra == 'dev'
Requires-Dist: pytest-cov (>=2.5.1) ; extra == 'dev'
Requires-Dist: pytest-runner (>=3.0) ; extra == 'dev'
Requires-Dist: pytest-xdist (>=1.20.1) ; extra == 'dev'
Requires-Dist: pytest (>=3.2.3) ; extra == 'dev'
Requires-Dist: google-compute-engine (==2.8.12) ; extra == 'dev'
Provides-Extra: tests
Requires-Dist: mock (>=2.0.0) ; extra == 'tests'
Requires-Dist: pytest-cov (>=2.5.1) ; extra == 'tests'
Requires-Dist: pytest-runner (>=3.0) ; extra == 'tests'
Requires-Dist: pytest-xdist (>=1.20.1) ; extra == 'tests'
Requires-Dist: pytest (>=3.2.3) ; extra == 'tests'
Requires-Dist: google-compute-engine (==2.8.12) ; extra == 'tests'
